evernote_backup/__init__.py
evernote_backup/__main__.py
evernote_backup/cli.py
evernote_backup/cli_app.py
evernote_backup/cli_app_auth.py
evernote_backup/cli_app_auth_oauth.py
evernote_backup/cli_app_auth_password.py
evernote_backup/cli_app_click_util.py
evernote_backup/cli_app_storage.py
evernote_backup/cli_app_util.py
evernote_backup/config.py
evernote_backup/config_defaults.py
evernote_backup/evernote_client.py
evernote_backup/evernote_client_api_http.py
evernote_backup/evernote_client_api_tokenized.py
evernote_backup/evernote_client_auth.py
evernote_backup/evernote_client_oauth.py
evernote_backup/evernote_client_sync.py
evernote_backup/evernote_client_util.py
evernote_backup/evernote_client_util_ssl.py
evernote_backup/evernote_types.py
evernote_backup/log_util.py
evernote_backup/note_checker.py
evernote_backup/note_exporter.py
evernote_backup/note_exporter_util.py
evernote_backup/note_formatter.py
evernote_backup/note_formatter_util.py
evernote_backup/note_lister.py
evernote_backup/note_storage.py
evernote_backup/note_synchronizer.py
evernote_backup/token_util.py
evernote_backup/version.py
evernote_backup-1.13.1.dist-info/LICENSE
evernote_backup-1.13.1.dist-info/METADATA
evernote_backup-1.13.1.dist-info/WHEEL
evernote_backup-1.13.1.dist-info/entry_points.txt
evernote_backup-1.13.1.dist-info/RECORD
