Metadata-Version: 2.3
Name: evernote-backup
Version: 1.13.1
Summary: Backup & export all Evernote notes and notebooks.
License: MIT
Keywords: evernote,yinxiang,backup,export,enex
Author: vzhd1701
Author-email: vzhd1701@gmail.com
Requires-Python: >=3.9,<4.0
Classifier: License :: OSI Approved :: MIT License
Classifier: Programming Language :: Python :: 3
Classifier: Programming Language :: Python :: 3.9
Classifier: Programming Language :: Python :: 3.10
Classifier: Programming Language :: Python :: 3.11
Classifier: Programming Language :: Python :: 3.12
Classifier: Programming Language :: Python :: 3.13
Classifier: Development Status :: 4 - Beta
Classifier: Intended Audience :: End Users/Desktop
Classifier: Natural Language :: English
Classifier: Environment :: Console
Classifier: Operating System :: MacOS
Classifier: Operating System :: Microsoft :: Windows
Classifier: Operating System :: POSIX :: Linux
Classifier: Topic :: Internet
Classifier: Topic :: System :: Archiving :: Backup
Classifier: Topic :: Terminals
Classifier: Topic :: Utilities
Requires-Dist: click (==8.1.8)
Requires-Dist: click-option-group (==0.5.7)
Requires-Dist: evernote-plus (==1.28.1.dev2)
Requires-Dist: requests-oauthlib (==1.3.1)
Requires-Dist: requests-sse (==0.5.1)
Requires-Dist: thrift (==0.21.0)
Requires-Dist: xmltodict (==0.13.0)
Project-URL: Repository, https://github.com/vzhd1701/evernote-backup
Project-URL: changelog, https://github.com/vzhd1701/evernote-backup/blob/master/CHANGELOG.md
